<?xml version="1.0" encoding="UTF-8"?>
<objects serializationModel="Studio.02.00.00">
	<object class="AudioFile" id="{a5857f39-bb08-4c9c-9d05-2d230b752eb7}">
		<property name="assetPath">
			<value>UI/ui_click_02.wav</value>
		</property>
		<property name="frequencyInKHz">
			<value>44.0999985</value>
		</property>
		<property name="channelCount">
			<value>1</value>
		</property>
		<property name="length">
			<value>0.034875283446712022</value>
		</property>
		<relationship name="masterAssetFolder">
			<destination>{7a95374c-c27f-45bd-af1b-2909bfac3168}</destination>
		</relationship>
	</object>
</objects>
