<?xml version="1.0" encoding="UTF-8"?>
<objects serializationModel="Studio.02.00.00">
	<object class="Snapshot" id="{a94ae2de-dc1c-4def-8e24-11c3984536ef}">
		<property name="name">
			<value>Endroom</value>
		</property>
		<relationship name="mixer">
			<destination>{b3a46157-4f7c-447c-b2ce-ad5eb3d9eedb}</destination>
		</relationship>
		<relationship name="automatableProperties">
			<destination>{75659fe9-2bf6-4515-a93f-8c0fec6dd9ab}</destination>
		</relationship>
		<relationship name="markerTracks">
			<destination>{985cb14a-105d-46f6-bca5-119543a2d4ac}</destination>
		</relationship>
		<relationship name="timeline">
			<destination>{7bd99973-5153-458b-812d-680896e5ff50}</destination>
		</relationship>
		<relationship name="snapshotMasterTrack">
			<destination>{c91681e9-1ca2-41e6-8704-177f5b2fefad}</destination>
		</relationship>
		<relationship name="snapshotProperties">
			<destination>{ed90f14f-c95c-4d6e-b617-a2705392ac48}</destination>
		</relationship>
		<relationship name="snapshotTracks">
			<destination>{436ee1f2-9f77-405d-9404-78017fc28604}</destination>
		</relationship>
	</object>
	<object class="EventAutomatableProperties" id="{75659fe9-2bf6-4515-a93f-8c0fec6dd9ab}" />
	<object class="MarkerTrack" id="{985cb14a-105d-46f6-bca5-119543a2d4ac}" />
	<object class="Timeline" id="{7bd99973-5153-458b-812d-680896e5ff50}" />
	<object class="SnapshotMasterTrack" id="{c91681e9-1ca2-41e6-8704-177f5b2fefad}" />
	<object class="SnapshotProperty" id="{ed90f14f-c95c-4d6e-b617-a2705392ac48}">
		<property name="propertyName">
			<value>decayTime</value>
		</property>
		<property name="value">
			<value>2200</value>
		</property>
		<relationship name="automatableObject">
			<destination>{1a0b4fa1-9631-4f30-961d-13203ee25003}</destination>
		</relationship>
	</object>
	<object class="SnapshotTrack" id="{436ee1f2-9f77-405d-9404-78017fc28604}">
		<relationship name="mixerStrip">
			<destination>{62132562-1dea-4e31-b005-242056322e48}</destination>
		</relationship>
	</object>
</objects>
